simple_colors.py
simple_colors-0.1.4.dist-info/DESCRIPTION.rst
simple_colors-0.1.4.dist-info/METADATA
simple_colors-0.1.4.dist-info/RECORD
simple_colors-0.1.4.dist-info/WHEEL
simple_colors-0.1.4.dist-info/entry_points.txt
simple_colors-0.1.4.dist-info/metadata.json
simple_colors-0.1.4.dist-info/top_level.txt
