Metadata-Version: 2.0
Name: simple-colors
Version: 0.1.4
Summary: Colorful output in terminal
Home-page: https://github.com/weaming/simple-colors
Author: weaming
Author-email: garden.yuen@gmail.com
License: UNKNOWN
Keywords: terminal
Platform: UNKNOWN
